blip_caption.py
blip_caption-0.1.dist-info/METADATA
blip_caption-0.1.dist-info/WHEEL
blip_caption-0.1.dist-info/entry_points.txt
blip_caption-0.1.dist-info/top_level.txt
blip_caption-0.1.dist-info/RECORD
