Metadata-Version: 2.1
Name: blip-caption
Version: 0.1
Summary: Generate captions for images with Salesforce BLIP
Author: Simon Willison
License: Apache-2.0
Project-URL: Homepage, https://github.com/simonw/blip-caption
Project-URL: Changelog, https://github.com/simonw/blip-caption/releases
Project-URL: Issues, https://github.com/simonw/blip-caption/issues
Classifier: Development Status :: 2 - Pre-Alpha
Requires-Dist: transformers
Requires-Dist: click
Requires-Dist: torch
Requires-Dist: pillow
Provides-Extra: test
Requires-Dist: pytest ; extra == 'test'
Requires-Dist: pytest-mock ; extra == 'test'
